cpf_and_cnpj_generator/__init__.py
cpf_and_cnpj_generator/cnpj_generator.py
cpf_and_cnpj_generator/cpf_generator.py
cpf_and_cnpj_generator-0.0.3.dist-info/LICENSE
cpf_and_cnpj_generator-0.0.3.dist-info/METADATA
cpf_and_cnpj_generator-0.0.3.dist-info/WHEEL
cpf_and_cnpj_generator-0.0.3.dist-info/top_level.txt
cpf_and_cnpj_generator-0.0.3.dist-info/RECORD
