Metadata-Version: 2.1
Name: cpf-and-cnpj-generator
Version: 0.0.3
Summary: This pypi package provides Python functions to generate valid Brazilian CPF (Cadastro de Pessoas Físicas) and CNPJ (Cadastro Nacional da Pessoa Jurídica) numbers.
Author: Gabriel Logan
License: MIT License
Project-URL: Homepage, https://gabriel-logan.github.io/Gerador-CPF-e-CNPJ-valido
Project-URL: Bug Tracker, https://github.com/gabriel-logan/Gerador-CPF-e-CNPJ-valido/tree/main/packages/python
Keywords: CPF,CNPJ,GENERATOR,GERADOR,VALIDADOR,DOCUMENTO,Python,Dados pessoais,npm,cpf,cnpj,gerador de cpf,gerador de cnpj,validador de cpf,validador de cnpj,gerador de cpf e cnpj,validador de cpf e cnpj,front-end,back-end
Classifier: Programming Language :: Python :: 3
Classifier: License :: OSI Approved :: MIT License
Classifier: Operating System :: OS Independent
Requires-Python: >=3.1
License-File: LICENSE
